gitsynclib
