Metadata-Version: 1.1
Name: GitSyncLib
Version: 0.1.4
Summary: GitSyncLib is a library that supports GitSync.
Home-page: https://github.com/jachin/GitSyncLib
Author: Jachin Rupe
Author-email: jachin@clockwork.net
License: MIT
Platform: UNKNOWN
Classifier: Intended Audience :: Developers
Classifier: Development Status :: 4 - Beta
Classifier: License :: OSI Approved :: MIT License
Classifier: Natural Language :: English
Classifier: Topic :: Communications :: File Sharing
Classifier: Topic :: Utilities
